<?xml version="1.0" encoding="ISO-8859-1"?>

<carparkData>
  <Northwest>
    <carpark name="PARNELL" spaces="386"> </carpark>
    <carpark name="ILAC" spaces="719"> </carpark>
    <carpark name="JERVIS" spaces="635"> </carpark>
    <carpark name="ARNOTTS" spaces="354"> </carpark>
  </Northwest>

  <Northeast>
    <carpark name="MARLBORO" spaces="177"> </carpark>
    <carpark name="ABBEY" spaces=" "> </carpark>
  </Northeast>

  <Southwest>
    <carpark name="THOMASST" spaces=" "> </carpark>
    <carpark name="C/CHURCH" spaces="118"> </carpark>
  </Southwest>

  <Southeast>
    <carpark name="SETANTA" spaces="80"> </carpark>
    <carpark name="DAWSON" spaces="276"> </carpark>
    <carpark name="TRINITY" spaces="248"> </carpark>
    <carpark name="GREENRCS" spaces="1042"> </carpark>
    <carpark name="DRURY" spaces="429"> </carpark>
    <carpark name="B/THOMAS" spaces="234"> </carpark>
  </Southeast>

  <Timestamp>15:31:25 on Sunday 10/06/2018</Timestamp>
</carparkData>
