<?xml version="1.0" encoding="ISO-8859-1"?>

<carparkData>
  <Northwest>
    <carpark name="PARNELL" spaces="400"> </carpark>
    <carpark name="ILAC" spaces="678"> </carpark>
    <carpark name="JERVIS" spaces="637"> </carpark>
    <carpark name="ARNOTTS" spaces="100"> </carpark>
  </Northwest>

  <Northeast>
    <carpark name="MARLBORO" spaces="95"> </carpark>
    <carpark name="ABBEY" spaces="313"> </carpark>
  </Northeast>

  <Southwest>
    <carpark name="THOMASST" spaces=" "> </carpark>
    <carpark name="C/CHURCH" spaces="137"> </carpark>
  </Southwest>

  <Southeast>
    <carpark name="SETANTA" spaces="57"> </carpark>
    <carpark name="DAWSON" spaces="265"> </carpark>
    <carpark name="TRINITY" spaces="253"> </carpark>
    <carpark name="GREENRCS" spaces="939"> </carpark>
    <carpark name="DRURY" spaces="269"> </carpark>
    <carpark name="B/THOMAS" spaces="132"> </carpark>
  </Southeast>

  <Timestamp>13:17:50 on Sunday 16/10/2016</Timestamp>
</carparkData>
