<?xml version="1.0" encoding="ISO-8859-1"?>

<carparkData>
  <Northwest>
    <carpark name="PARNELL" spaces="332"> </carpark>
    <carpark name="ILAC" spaces="675"> </carpark>
    <carpark name="JERVIS" spaces="733"> </carpark>
    <carpark name="ARNOTTS" spaces="221"> </carpark>
  </Northwest>

  <Northeast>
    <carpark name="MARLBORO" spaces="403"> </carpark>
    <carpark name="ABBEY" spaces="51"> </carpark>
  </Northeast>

  <Southwest>
    <carpark name="THOMASST" spaces="185"> </carpark>
    <carpark name="C/CHURCH" spaces="91"> </carpark>
  </Southwest>

  <Southeast>
    <carpark name="SETANTA" spaces="133"> </carpark>
    <carpark name="DAWSON" spaces="215"> </carpark>
    <carpark name="TRINITY" spaces="294"> </carpark>
    <carpark name="GREENRCS" spaces="946"> </carpark>
    <carpark name="DRURY" spaces="303"> </carpark>
    <carpark name="B/THOMAS" spaces="203"> </carpark>
  </Southeast>

  <Timestamp>10:29:16 on Saturday 29/08/2015</Timestamp>
</carparkData>
