<?xml version="1.0" encoding="ISO-8859-1"?>

<carparkData>
  <Northwest>
    <carpark name="PARNELL" spaces="196"> </carpark>
    <carpark name="ILAC" spaces="943"> </carpark>
    <carpark name="JERVIS" spaces="833"> </carpark>
    <carpark name="ARNOTTS" spaces="326"> </carpark>
  </Northwest>

  <Northeast>
    <carpark name="MARLBORO" spaces="306"> </carpark>
    <carpark name="ABBEY" spaces=" "> </carpark>
  </Northeast>

  <Southwest>
    <carpark name="THOMASST" spaces="209"> </carpark>
    <carpark name="C/CHURCH" spaces="79"> </carpark>
  </Southwest>

  <Southeast>
    <carpark name="SETANTA" spaces="83"> </carpark>
    <carpark name="DAWSON" spaces="205"> </carpark>
    <carpark name="TRINITY" spaces="208"> </carpark>
    <carpark name="GREENRCS" spaces="713"> </carpark>
    <carpark name="DRURY" spaces="445"> </carpark>
    <carpark name="B/THOMAS" spaces="363"> </carpark>
  </Southeast>

  <Timestamp>08:50:40 on Monday 21/05/2018</Timestamp>
</carparkData>
