<?xml version="1.0" encoding="ISO-8859-1"?>

<carparkData>
  <Northwest>
    <carpark name="PARNELL" spaces="304"> </carpark>
    <carpark name="ILAC" spaces=" "> </carpark>
    <carpark name="JERVIS" spaces=" "> </carpark>
    <carpark name="ARNOTTS" spaces=" "> </carpark>
  </Northwest>

  <Northeast>
    <carpark name="MARLBORO" spaces="289"> </carpark>
    <carpark name="ABBEY" spaces="359"> </carpark>
  </Northeast>

  <Southwest>
    <carpark name="THOMASST" spaces=" "> </carpark>
    <carpark name="C/CHURCH" spaces="122"> </carpark>
  </Southwest>

  <Southeast>
    <carpark name="SETANTA" spaces="53"> </carpark>
    <carpark name="DAWSON" spaces="290"> </carpark>
    <carpark name="TRINITY" spaces="165"> </carpark>
    <carpark name="GREENRCS" spaces="1092"> </carpark>
    <carpark name="DRURY" spaces="328"> </carpark>
    <carpark name="B/THOMAS" spaces="295"> </carpark>
  </Southeast>

  <Timestamp>23:07:27 on Saturday 16/07/2016</Timestamp>
</carparkData>
