<?xml version="1.0" encoding="ISO-8859-1"?>

<carparkData>
  <Northwest>
    <carpark name="PARNELL" spaces="243"> </carpark>
    <carpark name="ILAC" spaces="901"> </carpark>
    <carpark name="JERVIS" spaces="784"> </carpark>
    <carpark name="ARNOTTS" spaces="337"> </carpark>
  </Northwest>

  <Northeast>
    <carpark name="MARLBORO" spaces="160"> </carpark>
    <carpark name="ABBEY" spaces=" "> </carpark>
  </Northeast>

  <Southwest>
    <carpark name="THOMASST" spaces="212"> </carpark>
    <carpark name="C/CHURCH" spaces="112"> </carpark>
  </Southwest>

  <Southeast>
    <carpark name="SETANTA" spaces="71"> </carpark>
    <carpark name="DAWSON" spaces="211"> </carpark>
    <carpark name="TRINITY" spaces="238"> </carpark>
    <carpark name="GREENRCS" spaces="856"> </carpark>
    <carpark name="DRURY" spaces="223"> </carpark>
    <carpark name="B/THOMAS" spaces="347"> </carpark>
  </Southeast>

  <Timestamp>09:16:50 on Friday 31/05/2019</Timestamp>
</carparkData>
