<?xml version="1.0" encoding="ISO-8859-1"?>

<carparkData>
  <Northwest>
    <carpark name="PARNELL" spaces="115"> </carpark>
    <carpark name="ILAC" spaces="684"> </carpark>
    <carpark name="JERVIS" spaces="588"> </carpark>
    <carpark name="ARNOTTS" spaces="313"> </carpark>
  </Northwest>

  <Northeast>
    <carpark name="MARLBORO" spaces="45"> </carpark>
    <carpark name="ABBEY" spaces=" "> </carpark>
  </Northeast>

  <Southwest>
    <carpark name="THOMASST" spaces="175"> </carpark>
    <carpark name="C/CHURCH" spaces="41"> </carpark>
  </Southwest>

  <Southeast>
    <carpark name="SETANTA" spaces="FULL"> </carpark>
    <carpark name="DAWSON" spaces="95"> </carpark>
    <carpark name="TRINITY" spaces="146"> </carpark>
    <carpark name="GREENRCS" spaces="499"> </carpark>
    <carpark name="DRURY" spaces="300"> </carpark>
    <carpark name="B/THOMAS" spaces="261"> </carpark>
  </Southeast>

  <Timestamp>11:21:25 on Tuesday 12/06/2018</Timestamp>
</carparkData>
