<?xml version="1.0" encoding="ISO-8859-1"?>

<carparkData>
  <Northwest>
    <carpark name="PARNELL" spaces="31"> </carpark>
    <carpark name="ILAC" spaces="721"> </carpark>
    <carpark name="JERVIS" spaces="554"> </carpark>
    <carpark name="ARNOTTS" spaces="291"> </carpark>
  </Northwest>

  <Northeast>
    <carpark name="MARLBORO" spaces="211"> </carpark>
    <carpark name="ABBEY" spaces=" "> </carpark>
  </Northeast>

  <Southwest>
    <carpark name="THOMASST" spaces="185"> </carpark>
    <carpark name="C/CHURCH" spaces="16"> </carpark>
  </Southwest>

  <Southeast>
    <carpark name="SETANTA" spaces=" "> </carpark>
    <carpark name="DAWSON" spaces="FULL"> </carpark>
    <carpark name="TRINITY" spaces="159"> </carpark>
    <carpark name="GREENRCS" spaces=" "> </carpark>
    <carpark name="DRURY" spaces="FULL"> </carpark>
    <carpark name="B/THOMAS" spaces=" "> </carpark>
  </Southeast>

  <Timestamp>12:17:06 on Friday 01/02/2019</Timestamp>
</carparkData>
