<?xml version="1.0" encoding="ISO-8859-1"?>

<carparkData>
  <Northwest>
    <carpark name="PARNELL" spaces="125"> </carpark>
    <carpark name="ILAC" spaces="937"> </carpark>
    <carpark name="JERVIS" spaces="530"> </carpark>
    <carpark name="ARNOTTS" spaces="356"> </carpark>
  </Northwest>

  <Northeast>
    <carpark name="MARLBORO" spaces="320"> </carpark>
    <carpark name="ABBEY" spaces=" "> </carpark>
  </Northeast>

  <Southwest>
    <carpark name="THOMASST" spaces="230"> </carpark>
    <carpark name="C/CHURCH" spaces="112"> </carpark>
  </Southwest>

  <Southeast>
    <carpark name="SETANTA" spaces="25"> </carpark>
    <carpark name="DAWSON" spaces="167"> </carpark>
    <carpark name="TRINITY" spaces="243"> </carpark>
    <carpark name="GREENRCS" spaces=" "> </carpark>
    <carpark name="DRURY" spaces="137"> </carpark>
    <carpark name="B/THOMAS" spaces="315"> </carpark>
  </Southeast>

  <Timestamp>18:16:59 on Wednesday 06/03/2019</Timestamp>
</carparkData>
