<?xml version="1.0" encoding="ISO-8859-1"?>

<carparkData>
  <Northwest>
    <carpark name="PARNELL" spaces="407"> </carpark>
    <carpark name="ILAC" spaces="984"> </carpark>
    <carpark name="JERVIS" spaces="946"> </carpark>
    <carpark name="ARNOTTS" spaces="338"> </carpark>
  </Northwest>

  <Northeast>
    <carpark name="MARLBORO" spaces="247"> </carpark>
    <carpark name="ABBEY" spaces="326"> </carpark>
  </Northeast>

  <Southwest>
    <carpark name="THOMASST" spaces="249"> </carpark>
    <carpark name="C/CHURCH" spaces="137"> </carpark>
  </Southwest>

  <Southeast>
    <carpark name="SETANTA" spaces="FULL"> </carpark>
    <carpark name="DAWSON" spaces="258"> </carpark>
    <carpark name="TRINITY" spaces="270"> </carpark>
    <carpark name="GREENRCS" spaces="989"> </carpark>
    <carpark name="DRURY" spaces="431"> </carpark>
    <carpark name="B/THOMAS" spaces="354"> </carpark>
  </Southeast>

  <Timestamp>07:42:24 on Monday 22/08/2016</Timestamp>
</carparkData>
