<?xml version="1.0" encoding="ISO-8859-1"?>

<carparkData>
  <Northwest>
    <carpark name="PARNELL" spaces="255"> </carpark>
    <carpark name="ILAC" spaces="739"> </carpark>
    <carpark name="JERVIS" spaces="719"> </carpark>
    <carpark name="ARNOTTS" spaces="297"> </carpark>
  </Northwest>

  <Northeast>
    <carpark name="MARLBORO" spaces="393"> </carpark>
    <carpark name="ABBEY" spaces=" "> </carpark>
  </Northeast>

  <Southwest>
    <carpark name="THOMASST" spaces="229"> </carpark>
    <carpark name="C/CHURCH" spaces="122"> </carpark>
  </Southwest>

  <Southeast>
    <carpark name="SETANTA" spaces="46"> </carpark>
    <carpark name="DAWSON" spaces="213"> </carpark>
    <carpark name="TRINITY" spaces="251"> </carpark>
    <carpark name="GREENRCS" spaces="820"> </carpark>
    <carpark name="DRURY" spaces="125"> </carpark>
    <carpark name="B/THOMAS" spaces="264"> </carpark>
  </Southeast>

  <Timestamp>10:36:49 on Saturday 21/04/2018</Timestamp>
</carparkData>
