<?xml version="1.0" encoding="ISO-8859-1"?>

<carparkData>
  <Northwest>
    <carpark name="PARNELL" spaces="162"> </carpark>
    <carpark name="ILAC" spaces="481"> </carpark>
    <carpark name="JERVIS" spaces="401"> </carpark>
    <carpark name="ARNOTTS" spaces="91"> </carpark>
  </Northwest>

  <Northeast>
    <carpark name="MARLBORO" spaces="282"> </carpark>
    <carpark name="ABBEY" spaces="263"> </carpark>
  </Northeast>

  <Southwest>
    <carpark name="THOMASST" spaces="222"> </carpark>
    <carpark name="C/CHURCH" spaces="91"> </carpark>
  </Southwest>

  <Southeast>
    <carpark name="SETANTA" spaces="FULL"> </carpark>
    <carpark name="DAWSON" spaces="139"> </carpark>
    <carpark name="TRINITY" spaces="345"> </carpark>
    <carpark name="GREENRCS" spaces="616"> </carpark>
    <carpark name="DRURY" spaces="17"> </carpark>
    <carpark name="B/THOMAS" spaces="41"> </carpark>
  </Southeast>

  <Timestamp>15:38:08 on Saturday 13/02/2016</Timestamp>
</carparkData>
