<?xml version="1.0" encoding="ISO-8859-1"?>

<carparkData>
  <Northwest>
    <carpark name="PARNELL" spaces="402"> </carpark>
    <carpark name="ILAC" spaces="991"> </carpark>
    <carpark name="JERVIS" spaces="938"> </carpark>
    <carpark name="ARNOTTS" spaces="336"> </carpark>
  </Northwest>

  <Northeast>
    <carpark name="MARLBORO" spaces="173"> </carpark>
    <carpark name="ABBEY" spaces=" "> </carpark>
  </Northeast>

  <Southwest>
    <carpark name="THOMASST" spaces="228"> </carpark>
    <carpark name="C/CHURCH" spaces="89"> </carpark>
  </Southwest>

  <Southeast>
    <carpark name="SETANTA" spaces="87"> </carpark>
    <carpark name="DAWSON" spaces="294"> </carpark>
    <carpark name="TRINITY" spaces="265"> </carpark>
    <carpark name="GREENRCS" spaces="FULL"> </carpark>
    <carpark name="DRURY" spaces="396"> </carpark>
    <carpark name="B/THOMAS" spaces="365"> </carpark>
  </Southeast>

  <Timestamp>07:37:58 on Monday 15/04/2019</Timestamp>
</carparkData>
