<?xml version="1.0" encoding="ISO-8859-1"?>

<carparkData>
  <Northwest>
    <carpark name="PARNELL" spaces="101"> </carpark>
    <carpark name="ILAC" spaces="768"> </carpark>
    <carpark name="JERVIS" spaces="625"> </carpark>
    <carpark name="ARNOTTS" spaces="211"> </carpark>
  </Northwest>

  <Northeast>
    <carpark name="MARLBORO" spaces="104"> </carpark>
    <carpark name="ABBEY" spaces=" "> </carpark>
  </Northeast>

  <Southwest>
    <carpark name="THOMASST" spaces="212"> </carpark>
    <carpark name="C/CHURCH" spaces="122"> </carpark>
  </Southwest>

  <Southeast>
    <carpark name="SETANTA" spaces="40"> </carpark>
    <carpark name="DAWSON" spaces="132"> </carpark>
    <carpark name="TRINITY" spaces="187"> </carpark>
    <carpark name="GREENRCS" spaces="616"> </carpark>
    <carpark name="DRURY" spaces="195"> </carpark>
    <carpark name="B/THOMAS" spaces="247"> </carpark>
  </Southeast>

  <Timestamp>11:14:13 on Monday 08/01/2018</Timestamp>
</carparkData>
