<?xml version="1.0" encoding="ISO-8859-1"?>

<carparkData>
  <Northwest>
    <carpark name="PARNELL" spaces="70"> </carpark>
    <carpark name="ILAC" spaces="430"> </carpark>
    <carpark name="JERVIS" spaces="298"> </carpark>
    <carpark name="ARNOTTS" spaces="270"> </carpark>
  </Northwest>

  <Northeast>
    <carpark name="MARLBORO" spaces="123"> </carpark>
    <carpark name="ABBEY" spaces=" "> </carpark>
  </Northeast>

  <Southwest>
    <carpark name="THOMASST" spaces="195"> </carpark>
    <carpark name="C/CHURCH" spaces="FULL"> </carpark>
  </Southwest>

  <Southeast>
    <carpark name="SETANTA" spaces="FULL"> </carpark>
    <carpark name="DAWSON" spaces="FULL"> </carpark>
    <carpark name="TRINITY" spaces="166"> </carpark>
    <carpark name="GREENRCS" spaces="326"> </carpark>
    <carpark name="DRURY" spaces="FULL"> </carpark>
    <carpark name="B/THOMAS" spaces="67"> </carpark>
  </Southeast>

  <Timestamp>12:36:28 on Thursday 13/12/2018</Timestamp>
</carparkData>
