<?xml version="1.0" encoding="ISO-8859-1"?>

<carparkData>
  <Northwest>
    <carpark name="PARNELL" spaces="358"> </carpark>
    <carpark name="ILAC" spaces=" "> </carpark>
    <carpark name="JERVIS" spaces="541"> </carpark>
    <carpark name="ARNOTTS" spaces=" "> </carpark>
  </Northwest>

  <Northeast>
    <carpark name="MARLBORO" spaces="239"> </carpark>
    <carpark name="ABBEY" spaces=" "> </carpark>
  </Northeast>

  <Southwest>
    <carpark name="THOMASST" spaces=" "> </carpark>
    <carpark name="C/CHURCH" spaces="105"> </carpark>
  </Southwest>

  <Southeast>
    <carpark name="SETANTA" spaces="138"> </carpark>
    <carpark name="DAWSON" spaces="293"> </carpark>
    <carpark name="TRINITY" spaces="228"> </carpark>
    <carpark name="GREENRCS" spaces=" "> </carpark>
    <carpark name="DRURY" spaces="294"> </carpark>
    <carpark name="B/THOMAS" spaces=" "> </carpark>
  </Southeast>

  <Timestamp>20:06:50 on Friday 31/05/2019</Timestamp>
</carparkData>
