<?xml version="1.0" encoding="ISO-8859-1"?>

<carparkData>
  <Northwest>
    <carpark name="PARNELL" spaces="161"> </carpark>
    <carpark name="ILAC" spaces="738"> </carpark>
    <carpark name="JERVIS" spaces="575"> </carpark>
    <carpark name="ARNOTTS" spaces="357"> </carpark>
  </Northwest>

  <Northeast>
    <carpark name="MARLBORO" spaces="237"> </carpark>
    <carpark name="ABBEY" spaces=" "> </carpark>
  </Northeast>

  <Southwest>
    <carpark name="THOMASST" spaces="201"> </carpark>
    <carpark name="C/CHURCH" spaces=" "> </carpark>
  </Southwest>

  <Southeast>
    <carpark name="SETANTA" spaces="FULL"> </carpark>
    <carpark name="DAWSON" spaces="95"> </carpark>
    <carpark name="TRINITY" spaces="162"> </carpark>
    <carpark name="GREENRCS" spaces=" "> </carpark>
    <carpark name="DRURY" spaces="40"> </carpark>
    <carpark name="B/THOMAS" spaces=" "> </carpark>
  </Southeast>

  <Timestamp>14:37:06 on Friday 25/01/2019</Timestamp>
</carparkData>
