<?xml version="1.0" encoding="ISO-8859-1"?>

<carparkData>
  <Northwest>
    <carpark name="PARNELL" spaces="374"> </carpark>
    <carpark name="ILAC" spaces="940"> </carpark>
    <carpark name="JERVIS" spaces="901"> </carpark>
    <carpark name="ARNOTTS" spaces="274"> </carpark>
  </Northwest>

  <Northeast>
    <carpark name="MARLBORO" spaces="405"> </carpark>
    <carpark name="ABBEY" spaces="259"> </carpark>
  </Northeast>

  <Southwest>
    <carpark name="THOMASST" spaces=" "> </carpark>
    <carpark name="C/CHURCH" spaces="40"> </carpark>
  </Southwest>

  <Southeast>
    <carpark name="SETANTA" spaces="89"> </carpark>
    <carpark name="DAWSON" spaces="309"> </carpark>
    <carpark name="TRINITY" spaces="267"> </carpark>
    <carpark name="GREENRCS" spaces="1037"> </carpark>
    <carpark name="DRURY" spaces="399"> </carpark>
    <carpark name="B/THOMAS" spaces="321"> </carpark>
  </Southeast>

  <Timestamp>18:05:54 on Sunday 07/05/2017</Timestamp>
</carparkData>
