<?xml version="1.0" encoding="ISO-8859-1"?>

<carparkData>
  <Northwest>
    <carpark name="PARNELL" spaces="25"> </carpark>
    <carpark name="ILAC" spaces="488"> </carpark>
    <carpark name="JERVIS" spaces="216"> </carpark>
    <carpark name="ARNOTTS" spaces="306"> </carpark>
  </Northwest>

  <Northeast>
    <carpark name="MARLBORO" spaces="171"> </carpark>
    <carpark name="ABBEY" spaces=" "> </carpark>
  </Northeast>

  <Southwest>
    <carpark name="THOMASST" spaces="183"> </carpark>
    <carpark name="C/CHURCH" spaces="19"> </carpark>
  </Southwest>

  <Southeast>
    <carpark name="SETANTA" spaces="FULL"> </carpark>
    <carpark name="DAWSON" spaces="15"> </carpark>
    <carpark name="TRINITY" spaces="132"> </carpark>
    <carpark name="GREENRCS" spaces="359"> </carpark>
    <carpark name="DRURY" spaces="FULL"> </carpark>
    <carpark name="B/THOMAS" spaces="117"> </carpark>
  </Southeast>

  <Timestamp>13:35:08 on Thursday 06/12/2018</Timestamp>
</carparkData>
