<?xml version="1.0" encoding="ISO-8859-1"?>

<carparkData>
  <Northwest>
    <carpark name="PARNELL" spaces="339"> </carpark>
    <carpark name="ILAC" spaces="988"> </carpark>
    <carpark name="JERVIS" spaces="962"> </carpark>
    <carpark name="ARNOTTS" spaces="343"> </carpark>
  </Northwest>

  <Northeast>
    <carpark name="MARLBORO" spaces="209"> </carpark>
    <carpark name="ABBEY" spaces=" "> </carpark>
  </Northeast>

  <Southwest>
    <carpark name="THOMASST" spaces="224"> </carpark>
    <carpark name="C/CHURCH" spaces="100"> </carpark>
  </Southwest>

  <Southeast>
    <carpark name="SETANTA" spaces="107"> </carpark>
    <carpark name="DAWSON" spaces="315"> </carpark>
    <carpark name="TRINITY" spaces="261"> </carpark>
    <carpark name="GREENRCS" spaces="976"> </carpark>
    <carpark name="DRURY" spaces="530"> </carpark>
    <carpark name="B/THOMAS" spaces="383"> </carpark>
  </Southeast>

  <Timestamp>07:36:26 on Tuesday 07/08/2018</Timestamp>
</carparkData>
