<?xml version="1.0" encoding="ISO-8859-1"?>

<carparkData>
  <Northwest>
    <carpark name="PARNELL" spaces="246"> </carpark>
    <carpark name="ILAC" spaces="910"> </carpark>
    <carpark name="JERVIS" spaces="715"> </carpark>
    <carpark name="ARNOTTS" spaces="291"> </carpark>
  </Northwest>

  <Northeast>
    <carpark name="MARLBORO" spaces="238"> </carpark>
    <carpark name="ABBEY" spaces=" "> </carpark>
  </Northeast>

  <Southwest>
    <carpark name="THOMASST" spaces="215"> </carpark>
    <carpark name="C/CHURCH" spaces="122"> </carpark>
  </Southwest>

  <Southeast>
    <carpark name="SETANTA" spaces="79"> </carpark>
    <carpark name="DAWSON" spaces="189"> </carpark>
    <carpark name="TRINITY" spaces="219"> </carpark>
    <carpark name="GREENRCS" spaces="735"> </carpark>
    <carpark name="DRURY" spaces="319"> </carpark>
    <carpark name="B/THOMAS" spaces="343"> </carpark>
  </Southeast>

  <Timestamp>09:16:37 on Friday 01/09/2017</Timestamp>
</carparkData>
