<?xml version="1.0" encoding="ISO-8859-1"?>

<carparkData>
  <Northwest>
    <carpark name="PARNELL" spaces="284"> </carpark>
    <carpark name="ILAC" spaces="963"> </carpark>
    <carpark name="JERVIS" spaces="874"> </carpark>
    <carpark name="ARNOTTS" spaces="318"> </carpark>
  </Northwest>

  <Northeast>
    <carpark name="MARLBORO" spaces="74"> </carpark>
    <carpark name="ABBEY" spaces="291"> </carpark>
  </Northeast>

  <Southwest>
    <carpark name="THOMASST" spaces="190"> </carpark>
    <carpark name="C/CHURCH" spaces="151"> </carpark>
  </Southwest>

  <Southeast>
    <carpark name="SETANTA" spaces="FULL"> </carpark>
    <carpark name="DAWSON" spaces="238"> </carpark>
    <carpark name="TRINITY" spaces="303"> </carpark>
    <carpark name="GREENRCS" spaces="881"> </carpark>
    <carpark name="DRURY" spaces="401"> </carpark>
    <carpark name="B/THOMAS" spaces="363"> </carpark>
  </Southeast>

  <Timestamp>08:23:58 on Monday 23/05/2016</Timestamp>
</carparkData>
