<?xml version="1.0" encoding="ISO-8859-1"?>

<carparkData>
  <Northwest>
    <carpark name="PARNELL" spaces="267"> </carpark>
    <carpark name="ILAC" spaces="368"> </carpark>
    <carpark name="JERVIS" spaces="162"> </carpark>
    <carpark name="ARNOTTS" spaces="161"> </carpark>
  </Northwest>

  <Northeast>
    <carpark name="MARLBORO" spaces="311"> </carpark>
    <carpark name="ABBEY" spaces=" "> </carpark>
  </Northeast>

  <Southwest>
    <carpark name="THOMASST" spaces="199"> </carpark>
    <carpark name="C/CHURCH" spaces="68"> </carpark>
  </Southwest>

  <Southeast>
    <carpark name="SETANTA" spaces="24"> </carpark>
    <carpark name="DAWSON" spaces="103"> </carpark>
    <carpark name="TRINITY" spaces="140"> </carpark>
    <carpark name="GREENRCS" spaces="378"> </carpark>
    <carpark name="DRURY" spaces="FULL"> </carpark>
    <carpark name="B/THOMAS" spaces="FULL"> </carpark>
  </Southeast>

  <Timestamp>16:06:28 on Saturday 08/12/2018</Timestamp>
</carparkData>
