<?xml version="1.0" encoding="ISO-8859-1"?>

<carparkData>
  <Northwest>
    <carpark name="PARNELL" spaces="243"> </carpark>
    <carpark name="ILAC" spaces="609"> </carpark>
    <carpark name="JERVIS" spaces="528"> </carpark>
    <carpark name="ARNOTTS" spaces="103"> </carpark>
  </Northwest>

  <Northeast>
    <carpark name="MARLBORO" spaces="367"> </carpark>
    <carpark name="ABBEY" spaces="310"> </carpark>
  </Northeast>

  <Southwest>
    <carpark name="THOMASST" spaces="246"> </carpark>
    <carpark name="C/CHURCH" spaces="29"> </carpark>
  </Southwest>

  <Southeast>
    <carpark name="SETANTA" spaces="29"> </carpark>
    <carpark name="DAWSON" spaces="203"> </carpark>
    <carpark name="TRINITY" spaces="381"> </carpark>
    <carpark name="GREENRCS" spaces="731"> </carpark>
    <carpark name="DRURY" spaces="FULL"> </carpark>
    <carpark name="B/THOMAS" spaces="119"> </carpark>
  </Southeast>

  <Timestamp>17:32:08 on Monday 28/12/2015</Timestamp>
</carparkData>
