<?xml version="1.0" encoding="ISO-8859-1"?>

<carparkData>
  <Northwest>
    <carpark name="PARNELL" spaces="116"> </carpark>
    <carpark name="ILAC" spaces="582"> </carpark>
    <carpark name="JERVIS" spaces="513"> </carpark>
    <carpark name="ARNOTTS" spaces="278"> </carpark>
  </Northwest>

  <Northeast>
    <carpark name="MARLBORO" spaces="257"> </carpark>
    <carpark name="ABBEY" spaces=" "> </carpark>
  </Northeast>

  <Southwest>
    <carpark name="THOMASST" spaces="203"> </carpark>
    <carpark name="C/CHURCH" spaces="73"> </carpark>
  </Southwest>

  <Southeast>
    <carpark name="SETANTA" spaces=" "> </carpark>
    <carpark name="DAWSON" spaces="85"> </carpark>
    <carpark name="TRINITY" spaces="234"> </carpark>
    <carpark name="GREENRCS" spaces="562"> </carpark>
    <carpark name="DRURY" spaces="FULL"> </carpark>
    <carpark name="B/THOMAS" spaces="219"> </carpark>
  </Southeast>

  <Timestamp>10:30:28 on Monday 17/12/2018</Timestamp>
</carparkData>
