<?xml version="1.0" encoding="ISO-8859-1"?>

<carparkData>
  <Northwest>
    <carpark name="PARNELL" spaces="288"> </carpark>
    <carpark name="ILAC" spaces="962"> </carpark>
    <carpark name="JERVIS" spaces="641"> </carpark>
    <carpark name="ARNOTTS" spaces="323"> </carpark>
  </Northwest>

  <Northeast>
    <carpark name="MARLBORO" spaces="342"> </carpark>
    <carpark name="ABBEY" spaces="317"> </carpark>
  </Northeast>

  <Southwest>
    <carpark name="THOMASST" spaces="200"> </carpark>
    <carpark name="C/CHURCH" spaces="127"> </carpark>
  </Southwest>

  <Southeast>
    <carpark name="SETANTA" spaces="32"> </carpark>
    <carpark name="DAWSON" spaces="323"> </carpark>
    <carpark name="TRINITY" spaces="240"> </carpark>
    <carpark name="GREENRCS" spaces="1000"> </carpark>
    <carpark name="DRURY" spaces="362"> </carpark>
    <carpark name="B/THOMAS" spaces=" "> </carpark>
  </Southeast>

  <Timestamp>08:15:50 on Monday 19/09/2016</Timestamp>
</carparkData>
