<?xml version="1.0" encoding="ISO-8859-1"?>

<carparkData>
  <Northwest>
    <carpark name="PARNELL" spaces="43"> </carpark>
    <carpark name="ILAC" spaces="681"> </carpark>
    <carpark name="JERVIS" spaces="621"> </carpark>
    <carpark name="ARNOTTS" spaces="196"> </carpark>
  </Northwest>

  <Northeast>
    <carpark name="MARLBORO" spaces="34"> </carpark>
    <carpark name="ABBEY" spaces="129"> </carpark>
  </Northeast>

  <Southwest>
    <carpark name="THOMASST" spaces="206"> </carpark>
    <carpark name="C/CHURCH" spaces="22"> </carpark>
  </Southwest>

  <Southeast>
    <carpark name="SETANTA" spaces="FULL"> </carpark>
    <carpark name="DAWSON" spaces="119"> </carpark>
    <carpark name="TRINITY" spaces="338"> </carpark>
    <carpark name="GREENRCS" spaces="542"> </carpark>
    <carpark name="DRURY" spaces="145"> </carpark>
    <carpark name="B/THOMAS" spaces="188"> </carpark>
  </Southeast>

  <Timestamp>15:25:58 on Monday 25/04/2016</Timestamp>
</carparkData>
