<?xml version="1.0" encoding="ISO-8859-1"?>

<carparkData>
  <Northwest>
    <carpark name="PARNELL" spaces="101"> </carpark>
    <carpark name="ILAC" spaces="772"> </carpark>
    <carpark name="JERVIS" spaces="659"> </carpark>
    <carpark name="ARNOTTS" spaces="305"> </carpark>
  </Northwest>

  <Northeast>
    <carpark name="MARLBORO" spaces="123"> </carpark>
    <carpark name="ABBEY" spaces=" "> </carpark>
  </Northeast>

  <Southwest>
    <carpark name="THOMASST" spaces="186"> </carpark>
    <carpark name="C/CHURCH" spaces="81"> </carpark>
  </Southwest>

  <Southeast>
    <carpark name="SETANTA" spaces="36"> </carpark>
    <carpark name="DAWSON" spaces="140"> </carpark>
    <carpark name="TRINITY" spaces="169"> </carpark>
    <carpark name="GREENRCS" spaces="601"> </carpark>
    <carpark name="DRURY" spaces="134"> </carpark>
    <carpark name="B/THOMAS" spaces=" "> </carpark>
  </Southeast>

  <Timestamp>10:30:33 on Tuesday 13/03/2018</Timestamp>
</carparkData>
