<?xml version="1.0" encoding="ISO-8859-1"?>

<carparkData>
  <Northwest>
    <carpark name="PARNELL" spaces="210"> </carpark>
    <carpark name="ILAC" spaces="826"> </carpark>
    <carpark name="JERVIS" spaces="725"> </carpark>
    <carpark name="ARNOTTS" spaces="92"> </carpark>
  </Northwest>

  <Northeast>
    <carpark name="MARLBORO" spaces="218"> </carpark>
    <carpark name="ABBEY" spaces="350"> </carpark>
  </Northeast>

  <Southwest>
    <carpark name="THOMASST" spaces=" "> </carpark>
    <carpark name="C/CHURCH" spaces="96"> </carpark>
  </Southwest>

  <Southeast>
    <carpark name="SETANTA" spaces="15"> </carpark>
    <carpark name="DAWSON" spaces="183"> </carpark>
    <carpark name="TRINITY" spaces="194"> </carpark>
    <carpark name="GREENRCS" spaces="767"> </carpark>
    <carpark name="DRURY" spaces="238"> </carpark>
    <carpark name="B/THOMAS" spaces="260"> </carpark>
  </Southeast>

  <Timestamp>17:13:00 on Friday 10/02/2017</Timestamp>
</carparkData>
