<?xml version="1.0" encoding="ISO-8859-1"?>

<carparkData>
  <Northwest>
    <carpark name="PARNELL" spaces="81"> </carpark>
    <carpark name="ILAC" spaces="663"> </carpark>
    <carpark name="JERVIS" spaces="560"> </carpark>
    <carpark name="ARNOTTS" spaces="99"> </carpark>
  </Northwest>

  <Northeast>
    <carpark name="MARLBORO" spaces="173"> </carpark>
    <carpark name="ABBEY" spaces="169"> </carpark>
  </Northeast>

  <Southwest>
    <carpark name="THOMASST" spaces="194"> </carpark>
    <carpark name="C/CHURCH" spaces="29"> </carpark>
  </Southwest>

  <Southeast>
    <carpark name="SETANTA" spaces="FULL"> </carpark>
    <carpark name="DAWSON" spaces="59"> </carpark>
    <carpark name="TRINITY" spaces="337"> </carpark>
    <carpark name="GREENRCS" spaces="567"> </carpark>
    <carpark name="DRURY" spaces="167"> </carpark>
    <carpark name="B/THOMAS" spaces="105"> </carpark>
  </Southeast>

  <Timestamp>14:30:08 on Friday 29/01/2016</Timestamp>
</carparkData>
