<?xml version="1.0" encoding="ISO-8859-1"?>

<carparkData>
  <Northwest>
    <carpark name="PARNELL" spaces="71"> </carpark>
    <carpark name="ILAC" spaces="661"> </carpark>
    <carpark name="JERVIS" spaces="527"> </carpark>
    <carpark name="ARNOTTS" spaces="273"> </carpark>
  </Northwest>

  <Northeast>
    <carpark name="MARLBORO" spaces="157"> </carpark>
    <carpark name="ABBEY" spaces=" "> </carpark>
  </Northeast>

  <Southwest>
    <carpark name="THOMASST" spaces="194"> </carpark>
    <carpark name="C/CHURCH" spaces="92"> </carpark>
  </Southwest>

  <Southeast>
    <carpark name="SETANTA" spaces="45"> </carpark>
    <carpark name="DAWSON" spaces="102"> </carpark>
    <carpark name="TRINITY" spaces="153"> </carpark>
    <carpark name="GREENRCS" spaces="455"> </carpark>
    <carpark name="DRURY" spaces="73"> </carpark>
    <carpark name="B/THOMAS" spaces="241"> </carpark>
  </Southeast>

  <Timestamp>12:51:36 on Monday 12/02/2018</Timestamp>
</carparkData>
