<?xml version="1.0" encoding="ISO-8859-1"?>

<carparkData>
  <Northwest>
    <carpark name="PARNELL" spaces="186"> </carpark>
    <carpark name="ILAC" spaces="643"> </carpark>
    <carpark name="JERVIS" spaces="1024"> </carpark>
    <carpark name="ARNOTTS" spaces="183"> </carpark>
  </Northwest>

  <Northeast>
    <carpark name="MARLBORO" spaces="235"> </carpark>
    <carpark name="ABBEY" spaces="238"> </carpark>
  </Northeast>

  <Southwest>
    <carpark name="THOMASST" spaces="203"> </carpark>
    <carpark name="C/CHURCH" spaces="115"> </carpark>
  </Southwest>

  <Southeast>
    <carpark name="SETANTA" spaces=" "> </carpark>
    <carpark name="DAWSON" spaces="104"> </carpark>
    <carpark name="TRINITY" spaces="348"> </carpark>
    <carpark name="GREENRCS" spaces="565"> </carpark>
    <carpark name="DRURY" spaces="88"> </carpark>
    <carpark name="B/THOMAS" spaces="187"> </carpark>
  </Southeast>

  <Timestamp>15:59:58 on Friday 06/05/2016</Timestamp>
</carparkData>
