<?xml version="1.0" encoding="ISO-8859-1"?>

<carparkData>
  <Northwest>
    <carpark name="PARNELL" spaces="389"> </carpark>
    <carpark name="ILAC" spaces=" "> </carpark>
    <carpark name="JERVIS" spaces=" "> </carpark>
    <carpark name="ARNOTTS" spaces=" "> </carpark>
  </Northwest>

  <Northeast>
    <carpark name="MARLBORO" spaces="408"> </carpark>
    <carpark name="ABBEY" spaces="356"> </carpark>
  </Northeast>

  <Southwest>
    <carpark name="THOMASST" spaces=" "> </carpark>
    <carpark name="C/CHURCH" spaces="79"> </carpark>
  </Southwest>

  <Southeast>
    <carpark name="SETANTA" spaces="62"> </carpark>
    <carpark name="DAWSON" spaces="305"> </carpark>
    <carpark name="TRINITY" spaces="396"> </carpark>
    <carpark name="GREENRCS" spaces="861"> </carpark>
    <carpark name="DRURY" spaces="393"> </carpark>
    <carpark name="B/THOMAS" spaces=" "> </carpark>
  </Southeast>

  <Timestamp>21:10:08 on Tuesday 05/01/2016</Timestamp>
</carparkData>
