<?xml version="1.0" encoding="ISO-8859-1"?>

<carparkData>
  <Northwest>
    <carpark name="PARNELL" spaces="266"> </carpark>
    <carpark name="ILAC" spaces="929"> </carpark>
    <carpark name="JERVIS" spaces="848"> </carpark>
    <carpark name="ARNOTTS" spaces="350"> </carpark>
  </Northwest>

  <Northeast>
    <carpark name="MARLBORO" spaces="121"> </carpark>
    <carpark name="ABBEY" spaces=" "> </carpark>
  </Northeast>

  <Southwest>
    <carpark name="THOMASST" spaces="236"> </carpark>
    <carpark name="C/CHURCH" spaces="92"> </carpark>
  </Southwest>

  <Southeast>
    <carpark name="SETANTA" spaces="85"> </carpark>
    <carpark name="DAWSON" spaces="244"> </carpark>
    <carpark name="TRINITY" spaces="224"> </carpark>
    <carpark name="GREENRCS" spaces="905"> </carpark>
    <carpark name="DRURY" spaces="405"> </carpark>
    <carpark name="B/THOMAS" spaces=" "> </carpark>
  </Southeast>

  <Timestamp>18:36:25 on Friday 31/08/2018</Timestamp>
</carparkData>
