<?xml version="1.0" encoding="ISO-8859-1"?>

<carparkData>
  <Northwest>
    <carpark name="PARNELL" spaces="394"> </carpark>
    <carpark name="ILAC" spaces="956"> </carpark>
    <carpark name="JERVIS" spaces="897"> </carpark>
    <carpark name="ARNOTTS" spaces=" "> </carpark>
  </Northwest>

  <Northeast>
    <carpark name="MARLBORO" spaces="161"> </carpark>
    <carpark name="ABBEY" spaces="343"> </carpark>
  </Northeast>

  <Southwest>
    <carpark name="THOMASST" spaces=" "> </carpark>
    <carpark name="C/CHURCH" spaces="24"> </carpark>
  </Southwest>

  <Southeast>
    <carpark name="SETANTA" spaces="FULL"> </carpark>
    <carpark name="DAWSON" spaces="203"> </carpark>
    <carpark name="TRINITY" spaces="399"> </carpark>
    <carpark name="GREENRCS" spaces="1042"> </carpark>
    <carpark name="DRURY" spaces="99"> </carpark>
    <carpark name="B/THOMAS" spaces="297"> </carpark>
  </Southeast>

  <Timestamp>21:05:58 on Thursday 14/04/2016</Timestamp>
</carparkData>
