<?xml version="1.0" encoding="ISO-8859-1"?>

<carparkData>
  <Northwest>
    <carpark name="PARNELL" spaces=" "> </carpark>
    <carpark name="ILAC" spaces="590"> </carpark>
    <carpark name="JERVIS" spaces="487"> </carpark>
    <carpark name="ARNOTTS" spaces="127"> </carpark>
  </Northwest>

  <Northeast>
    <carpark name="MARLBORO" spaces="122"> </carpark>
    <carpark name="ABBEY" spaces="195"> </carpark>
  </Northeast>

  <Southwest>
    <carpark name="THOMASST" spaces="192"> </carpark>
    <carpark name="C/CHURCH" spaces="52"> </carpark>
  </Southwest>

  <Southeast>
    <carpark name="SETANTA" spaces="FULL"> </carpark>
    <carpark name="DAWSON" spaces="53"> </carpark>
    <carpark name="TRINITY" spaces="273"> </carpark>
    <carpark name="GREENRCS" spaces="528"> </carpark>
    <carpark name="DRURY" spaces="166"> </carpark>
    <carpark name="B/THOMAS" spaces="196"> </carpark>
  </Southeast>

  <Timestamp>12:52:31 on Tuesday 28/06/2016</Timestamp>
</carparkData>
