<?xml version="1.0" encoding="ISO-8859-1"?>

<carparkData>
  <Northwest>
    <carpark name="PARNELL" spaces="394"> </carpark>
    <carpark name="ILAC" spaces="966"> </carpark>
    <carpark name="JERVIS" spaces="952"> </carpark>
    <carpark name="ARNOTTS" spaces="317"> </carpark>
  </Northwest>

  <Northeast>
    <carpark name="MARLBORO" spaces="451"> </carpark>
    <carpark name="ABBEY" spaces="334"> </carpark>
  </Northeast>

  <Southwest>
    <carpark name="THOMASST" spaces="217"> </carpark>
    <carpark name="C/CHURCH" spaces="98"> </carpark>
  </Southwest>

  <Southeast>
    <carpark name="SETANTA" spaces="50"> </carpark>
    <carpark name="DAWSON" spaces="220"> </carpark>
    <carpark name="TRINITY" spaces="314"> </carpark>
    <carpark name="GREENRCS" spaces="1042"> </carpark>
    <carpark name="DRURY" spaces="387"> </carpark>
    <carpark name="B/THOMAS" spaces="293"> </carpark>
  </Southeast>

  <Timestamp>08:46:08 on Saturday 30/01/2016</Timestamp>
</carparkData>
