<?xml version="1.0" encoding="ISO-8859-1"?>

<carparkData>
  <Northwest>
    <carpark name="PARNELL" spaces="FULL"> </carpark>
    <carpark name="ILAC" spaces="549"> </carpark>
    <carpark name="JERVIS" spaces="499"> </carpark>
    <carpark name="ARNOTTS" spaces="71"> </carpark>
  </Northwest>

  <Northeast>
    <carpark name="MARLBORO" spaces="140"> </carpark>
    <carpark name="ABBEY" spaces="144"> </carpark>
  </Northeast>

  <Southwest>
    <carpark name="THOMASST" spaces="166"> </carpark>
    <carpark name="C/CHURCH" spaces="82"> </carpark>
  </Southwest>

  <Southeast>
    <carpark name="SETANTA" spaces="FULL"> </carpark>
    <carpark name="DAWSON" spaces="56"> </carpark>
    <carpark name="TRINITY" spaces="294"> </carpark>
    <carpark name="GREENRCS" spaces="499"> </carpark>
    <carpark name="DRURY" spaces="42"> </carpark>
    <carpark name="B/THOMAS" spaces="205"> </carpark>
  </Southeast>

  <Timestamp>12:50:08 on Friday 26/02/2016</Timestamp>
</carparkData>
