<?xml version="1.0" encoding="ISO-8859-1"?>

<carparkData>
  <Northwest>
    <carpark name="PARNELL" spaces="402"> </carpark>
    <carpark name="ILAC" spaces="600"> </carpark>
    <carpark name="JERVIS" spaces="338"> </carpark>
    <carpark name="ARNOTTS" spaces="291"> </carpark>
  </Northwest>

  <Northeast>
    <carpark name="MARLBORO" spaces="421"> </carpark>
    <carpark name="ABBEY" spaces=" "> </carpark>
  </Northeast>

  <Southwest>
    <carpark name="THOMASST" spaces=" "> </carpark>
    <carpark name="C/CHURCH" spaces="83"> </carpark>
  </Southwest>

  <Southeast>
    <carpark name="SETANTA" spaces="69"> </carpark>
    <carpark name="DAWSON" spaces="199"> </carpark>
    <carpark name="TRINITY" spaces="244"> </carpark>
    <carpark name="GREENRCS" spaces="722"> </carpark>
    <carpark name="DRURY" spaces="199"> </carpark>
    <carpark name="B/THOMAS" spaces="112"> </carpark>
  </Southeast>

  <Timestamp>13:50:11 on Sunday 30/12/2018</Timestamp>
</carparkData>
