<?xml version="1.0" encoding="ISO-8859-1"?>

<carparkData>
  <Northwest>
    <carpark name="PARNELL" spaces="215"> </carpark>
    <carpark name="ILAC" spaces=" "> </carpark>
    <carpark name="JERVIS" spaces=" "> </carpark>
    <carpark name="ARNOTTS" spaces="329"> </carpark>
  </Northwest>

  <Northeast>
    <carpark name="MARLBORO" spaces="379"> </carpark>
    <carpark name="ABBEY" spaces="243"> </carpark>
  </Northeast>

  <Southwest>
    <carpark name="THOMASST" spaces=" "> </carpark>
    <carpark name="C/CHURCH" spaces="115"> </carpark>
  </Southwest>

  <Southeast>
    <carpark name="SETANTA" spaces="FULL"> </carpark>
    <carpark name="DAWSON" spaces="269"> </carpark>
    <carpark name="TRINITY" spaces="394"> </carpark>
    <carpark name="GREENRCS" spaces="911"> </carpark>
    <carpark name="DRURY" spaces="137"> </carpark>
    <carpark name="B/THOMAS" spaces="301"> </carpark>
  </Southeast>

  <Timestamp>19:21:16 on Monday 28/09/2015</Timestamp>
</carparkData>
