<?xml version="1.0" encoding="ISO-8859-1"?>

<carparkData>
  <Northwest>
    <carpark name="PARNELL" spaces="217"> </carpark>
    <carpark name="ILAC" spaces="550"> </carpark>
    <carpark name="JERVIS" spaces="548"> </carpark>
    <carpark name="ARNOTTS" spaces="111"> </carpark>
  </Northwest>

  <Northeast>
    <carpark name="MARLBORO" spaces="314"> </carpark>
    <carpark name="ABBEY" spaces="320"> </carpark>
  </Northeast>

  <Southwest>
    <carpark name="THOMASST" spaces="245"> </carpark>
    <carpark name="C/CHURCH" spaces="37"> </carpark>
  </Southwest>

  <Southeast>
    <carpark name="SETANTA" spaces="FULL"> </carpark>
    <carpark name="DAWSON" spaces="163"> </carpark>
    <carpark name="TRINITY" spaces="395"> </carpark>
    <carpark name="GREENRCS" spaces="648"> </carpark>
    <carpark name="DRURY" spaces="FULL"> </carpark>
    <carpark name="B/THOMAS" spaces="23"> </carpark>
  </Southeast>

  <Timestamp>17:36:08 on Wednesday 30/12/2015</Timestamp>
</carparkData>
