<?xml version="1.0" encoding="ISO-8859-1"?>

<carparkData>
  <Northwest>
    <carpark name="PARNELL" spaces="271"> </carpark>
    <carpark name="ILAC" spaces="681"> </carpark>
    <carpark name="JERVIS" spaces="417"> </carpark>
    <carpark name="ARNOTTS" spaces="126"> </carpark>
  </Northwest>

  <Northeast>
    <carpark name="MARLBORO" spaces="340"> </carpark>
    <carpark name="ABBEY" spaces="302"> </carpark>
  </Northeast>

  <Southwest>
    <carpark name="THOMASST" spaces="186"> </carpark>
    <carpark name="C/CHURCH" spaces="104"> </carpark>
  </Southwest>

  <Southeast>
    <carpark name="SETANTA" spaces="17"> </carpark>
    <carpark name="DAWSON" spaces="199"> </carpark>
    <carpark name="TRINITY" spaces="394"> </carpark>
    <carpark name="GREENRCS" spaces="736"> </carpark>
    <carpark name="DRURY" spaces="178"> </carpark>
    <carpark name="B/THOMAS" spaces="86"> </carpark>
  </Southeast>

  <Timestamp>17:31:58 on Saturday 02/04/2016</Timestamp>
</carparkData>
