<?xml version="1.0" encoding="ISO-8859-1"?>

<carparkData>
  <Northwest>
    <carpark name="PARNELL" spaces="209"> </carpark>
    <carpark name="ILAC" spaces="548"> </carpark>
    <carpark name="JERVIS" spaces="530"> </carpark>
    <carpark name="ARNOTTS" spaces="107"> </carpark>
  </Northwest>

  <Northeast>
    <carpark name="MARLBORO" spaces="FULL"> </carpark>
    <carpark name="ABBEY" spaces="80"> </carpark>
  </Northeast>

  <Southwest>
    <carpark name="THOMASST" spaces=" "> </carpark>
    <carpark name="C/CHURCH" spaces="132"> </carpark>
  </Southwest>

  <Southeast>
    <carpark name="SETANTA" spaces="167"> </carpark>
    <carpark name="DAWSON" spaces="263"> </carpark>
    <carpark name="TRINITY" spaces="324"> </carpark>
    <carpark name="GREENRCS" spaces="861"> </carpark>
    <carpark name="DRURY" spaces="323"> </carpark>
    <carpark name="B/THOMAS" spaces="168"> </carpark>
  </Southeast>

  <Timestamp>16:09:16 on Sunday 06/09/2015</Timestamp>
</carparkData>
