<?xml version="1.0" encoding="ISO-8859-1"?>

<carparkData>
  <Northwest>
    <carpark name="PARNELL" spaces="353"> </carpark>
    <carpark name="ILAC" spaces="626"> </carpark>
    <carpark name="JERVIS" spaces="608"> </carpark>
    <carpark name="ARNOTTS" spaces="89"> </carpark>
  </Northwest>

  <Northeast>
    <carpark name="MARLBORO" spaces="259"> </carpark>
    <carpark name="ABBEY" spaces=" "> </carpark>
  </Northeast>

  <Southwest>
    <carpark name="THOMASST" spaces="231"> </carpark>
    <carpark name="C/CHURCH" spaces="127"> </carpark>
  </Southwest>

  <Southeast>
    <carpark name="SETANTA" spaces=" "> </carpark>
    <carpark name="DAWSON" spaces="181"> </carpark>
    <carpark name="TRINITY" spaces="270"> </carpark>
    <carpark name="GREENRCS" spaces="909"> </carpark>
    <carpark name="DRURY" spaces="122"> </carpark>
    <carpark name="B/THOMAS" spaces="118"> </carpark>
  </Southeast>

  <Timestamp>12:00:19 on Saturday 06/01/2018</Timestamp>
</carparkData>
