<?xml version="1.0" encoding="ISO-8859-1"?>

<carparkData>
  <Northwest>
    <carpark name="PARNELL" spaces="402"> </carpark>
    <carpark name="ILAC" spaces="912"> </carpark>
    <carpark name="JERVIS" spaces="886"> </carpark>
    <carpark name="ARNOTTS" spaces="305"> </carpark>
  </Northwest>

  <Northeast>
    <carpark name="MARLBORO" spaces="396"> </carpark>
    <carpark name="ABBEY" spaces=" "> </carpark>
  </Northeast>

  <Southwest>
    <carpark name="THOMASST" spaces="236"> </carpark>
    <carpark name="C/CHURCH" spaces="141"> </carpark>
  </Southwest>

  <Southeast>
    <carpark name="SETANTA" spaces="97"> </carpark>
    <carpark name="DAWSON" spaces="264"> </carpark>
    <carpark name="TRINITY" spaces="274"> </carpark>
    <carpark name="GREENRCS" spaces="1026"> </carpark>
    <carpark name="DRURY" spaces="214"> </carpark>
    <carpark name="B/THOMAS" spaces="326"> </carpark>
  </Southeast>

  <Timestamp>09:21:45 on Saturday 03/02/2018</Timestamp>
</carparkData>
